{
  "project_info": {
    "project_number": "581929652416",
    "project_id": "edunion-f43e8",
    "storage_bucket": "edunion-f43e8.appspot.com"
  },
  "client": [
    {
      "client_info": {
        "mobilesdk_app_id": "1:581929652416:android:39858926a527c3817d9d25",
        "android_client_info": {
          "package_name": "com.edunionapp"
        }
      },
      "oauth_client": [],
      "api_key": [
        {
          "current_key": "AIzaSyDgKHDRI35F5vU7J65jdDsJYG5lo8MGTEk"
        }
      ],
      "services": {
        "appinvite_service": {
          "other_platform_oauth_client": []
        }
      }
    }
  ],
  "configuration_version": "1"
}